[{"date":"2009-12-01T00:00:00","name":"EIRE","value":18946.0},{"date":"2010-01-01T00:00:00","name":"EIRE","value":58669.0},{"date":"2010-02-01T00:00:00","name":"EIRE","value":20415.0},{"date":"2010-03-01T00:00:00","name":"EIRE","value":21778.0},{"date":"2010-04-01T00:00:00","name":"EIRE","value":23357.0},{"date":"2010-05-01T00:00:00","name":"EIRE","value":18652.0},{"date":"2010-06-01T00:00:00","name":"EIRE","value":22449.0},{"date":"2010-07-01T00:00:00","name":"EIRE","value":34595.0},{"date":"2010-08-01T00:00:00","name":"EIRE","value":25405.0},{"date":"2010-09-01T00:00:00","name":"EIRE","value":35898.0},{"date":"2010-10-01T00:00:00","name":"EIRE","value":42246.0},{"date":"2010-11-01T00:00:00","name":"EIRE","value":30216.0},{"date":"2010-12-01T00:00:00","name":"EIRE","value":14816.0},{"date":"2011-01-01T00:00:00","name":"EIRE","value":21704.0},{"date":"2011-02-01T00:00:00","name":"EIRE","value":12083.0},{"date":"2011-03-01T00:00:00","name":"EIRE","value":18323.0},{"date":"2011-04-01T00:00:00","name":"EIRE","value":7270.0},{"date":"2011-05-01T00:00:00","name":"EIRE","value":17758.0},{"date":"2011-06-01T00:00:00","name":"EIRE","value":20713.0},{"date":"2011-07-01T00:00:00","name":"EIRE","value":42289.0},{"date":"2011-08-01T00:00:00","name":"EIRE","value":18053.0},{"date":"2011-09-01T00:00:00","name":"EIRE","value":42486.0},{"date":"2011-10-01T00:00:00","name":"EIRE","value":23817.0},{"date":"2011-11-01T00:00:00","name":"EIRE","value":29838.0},{"date":"2011-12-01T00:00:00","name":"EIRE","value":7140.0},{"date":"2012-01-01T00:00:00","name":"EIRE","value":21115.0},{"date":"2012-02-01T00:00:00","name":"EIRE","value":20804.0},{"date":"2012-03-01T00:00:00","name":"EIRE","value":20493.0},{"date":"2012-04-01T00:00:00","name":"EIRE","value":20183.0},{"date":"2012-05-01T00:00:00","name":"EIRE","value":19872.0},{"date":"2012-06-01T00:00:00","name":"EIRE","value":19561.0},{"date":"2012-07-01T00:00:00","name":"EIRE","value":19250.0},{"date":"2012-08-01T00:00:00","name":"EIRE","value":18939.0},{"date":"2012-09-01T00:00:00","name":"EIRE","value":18628.0},{"date":"2012-10-01T00:00:00","name":"EIRE","value":18318.0},{"date":"2012-11-01T00:00:00","name":"EIRE","value":18007.0},{"date":"2012-12-01T00:00:00","name":"EIRE","value":17696.0},{"date":"2009-12-01T00:00:00","name":"Netherlands","value":15045.0},{"date":"2010-01-01T00:00:00","name":"Netherlands","value":29167.0},{"date":"2010-02-01T00:00:00","name":"Netherlands","value":17210.0},{"date":"2010-03-01T00:00:00","name":"Netherlands","value":24241.0},{"date":"2010-04-01T00:00:00","name":"Netherlands","value":6336.0},{"date":"2010-05-01T00:00:00","name":"Netherlands","value":22221.0},{"date":"2010-06-01T00:00:00","name":"Netherlands","value":24134.0},{"date":"2010-07-01T00:00:00","name":"Netherlands","value":5385.0},{"date":"2010-08-01T00:00:00","name":"Netherlands","value":24881.0},{"date":"2010-09-01T00:00:00","name":"Netherlands","value":44773.0},{"date":"2010-10-01T00:00:00","name":"Netherlands","value":16857.0},{"date":"2010-11-01T00:00:00","name":"Netherlands","value":35629.0},{"date":"2010-12-01T00:00:00","name":"Netherlands","value":8932.0},{"date":"2011-01-01T00:00:00","name":"Netherlands","value":26596.0},{"date":"2011-02-01T00:00:00","name":"Netherlands","value":22831.0},{"date":"2011-03-01T00:00:00","name":"Netherlands","value":22206.0},{"date":"2011-04-01T00:00:00","name":"Netherlands","value":2886.0},{"date":"2011-05-01T00:00:00","name":"Netherlands","value":28942.0},{"date":"2011-06-01T00:00:00","name":"Netherlands","value":26753.0},{"date":"2011-07-01T00:00:00","name":"Netherlands","value":11.0},{"date":"2011-08-01T00:00:00","name":"Netherlands","value":40327.0},{"date":"2011-09-01T00:00:00","name":"Netherlands","value":26832.0},{"date":"2011-10-01T00:00:00","name":"Netherlands","value":40378.0},{"date":"2011-11-01T00:00:00","name":"Netherlands","value":25640.0},{"date":"2011-12-01T00:00:00","name":"Netherlands","value":11728.0},{"date":"2012-01-01T00:00:00","name":"Netherlands","value":24733.0},{"date":"2012-02-01T00:00:00","name":"Netherlands","value":24943.0},{"date":"2012-03-01T00:00:00","name":"Netherlands","value":25154.0},{"date":"2012-04-01T00:00:00","name":"Netherlands","value":25364.0},{"date":"2012-05-01T00:00:00","name":"Netherlands","value":25575.0},{"date":"2012-06-01T00:00:00","name":"Netherlands","value":25785.0},{"date":"2012-07-01T00:00:00","name":"Netherlands","value":25996.0},{"date":"2012-08-01T00:00:00","name":"Netherlands","value":26206.0},{"date":"2012-09-01T00:00:00","name":"Netherlands","value":26417.0},{"date":"2012-10-01T00:00:00","name":"Netherlands","value":26627.0},{"date":"2012-11-01T00:00:00","name":"Netherlands","value":26838.0},{"date":"2012-12-01T00:00:00","name":"Netherlands","value":27048.0},{"date":"2009-12-01T00:00:00","name":"Germany","value":9034.0},{"date":"2010-01-01T00:00:00","name":"Germany","value":11260.0},{"date":"2010-02-01T00:00:00","name":"Germany","value":7971.0},{"date":"2010-03-01T00:00:00","name":"Germany","value":15347.0},{"date":"2010-04-01T00:00:00","name":"Germany","value":21667.0},{"date":"2010-05-01T00:00:00","name":"Germany","value":8100.0},{"date":"2010-06-01T00:00:00","name":"Germany","value":14383.0},{"date":"2010-07-01T00:00:00","name":"Germany","value":18227.0},{"date":"2010-08-01T00:00:00","name":"Germany","value":8982.0},{"date":"2010-09-01T00:00:00","name":"Germany","value":16192.0},{"date":"2010-10-01T00:00:00","name":"Germany","value":19442.0},{"date":"2010-11-01T00:00:00","name":"Germany","value":27668.0},{"date":"2010-12-01T00:00:00","name":"Germany","value":18261.0},{"date":"2011-01-01T00:00:00","name":"Germany","value":15326.0},{"date":"2011-02-01T00:00:00","name":"Germany","value":8825.0},{"date":"2011-03-01T00:00:00","name":"Germany","value":12862.0},{"date":"2011-04-01T00:00:00","name":"Germany","value":10994.0},{"date":"2011-05-01T00:00:00","name":"Germany","value":23518.0},{"date":"2011-06-01T00:00:00","name":"Germany","value":12122.0},{"date":"2011-07-01T00:00:00","name":"Germany","value":14743.0},{"date":"2011-08-01T00:00:00","name":"Germany","value":17636.0},{"date":"2011-09-01T00:00:00","name":"Germany","value":16561.0},{"date":"2011-10-01T00:00:00","name":"Germany","value":28422.0},{"date":"2011-11-01T00:00:00","name":"Germany","value":24252.0},{"date":"2011-12-01T00:00:00","name":"Germany","value":7024.0},{"date":"2012-01-01T00:00:00","name":"Germany","value":18811.0},{"date":"2012-02-01T00:00:00","name":"Germany","value":19061.0},{"date":"2012-03-01T00:00:00","name":"Germany","value":19312.0},{"date":"2012-04-01T00:00:00","name":"Germany","value":19563.0},{"date":"2012-05-01T00:00:00","name":"Germany","value":19813.0},{"date":"2012-06-01T00:00:00","name":"Germany","value":20064.0},{"date":"2012-07-01T00:00:00","name":"Germany","value":20315.0},{"date":"2012-08-01T00:00:00","name":"Germany","value":20565.0},{"date":"2012-09-01T00:00:00","name":"Germany","value":20816.0},{"date":"2012-10-01T00:00:00","name":"Germany","value":21067.0},{"date":"2012-11-01T00:00:00","name":"Germany","value":21317.0},{"date":"2012-12-01T00:00:00","name":"Germany","value":21568.0},{"date":"2009-12-01T00:00:00","name":"France","value":5873.0},{"date":"2010-01-01T00:00:00","name":"France","value":7316.0},{"date":"2010-02-01T00:00:00","name":"France","value":8073.0},{"date":"2010-03-01T00:00:00","name":"France","value":8027.0},{"date":"2010-04-01T00:00:00","name":"France","value":7144.0},{"date":"2010-05-01T00:00:00","name":"France","value":13344.0},{"date":"2010-06-01T00:00:00","name":"France","value":8439.0},{"date":"2010-07-01T00:00:00","name":"France","value":7276.0},{"date":"2010-08-01T00:00:00","name":"France","value":16285.0},{"date":"2010-09-01T00:00:00","name":"France","value":12314.0},{"date":"2010-10-01T00:00:00","name":"France","value":14398.0},{"date":"2010-11-01T00:00:00","name":"France","value":18211.0},{"date":"2010-12-01T00:00:00","name":"France","value":14190.0},{"date":"2011-01-01T00:00:00","name":"France","value":16174.0},{"date":"2011-02-01T00:00:00","name":"France","value":7687.0},{"date":"2011-03-01T00:00:00","name":"France","value":13689.0},{"date":"2011-04-01T00:00:00","name":"France","value":3899.0},{"date":"2011-05-01T00:00:00","name":"France","value":16174.0},{"date":"2011-06-01T00:00:00","name":"France","value":14962.0},{"date":"2011-07-01T00:00:00","name":"France","value":9171.0},{"date":"2011-08-01T00:00:00","name":"France","value":12630.0},{"date":"2011-09-01T00:00:00","name":"France","value":21898.0},{"date":"2011-10-01T00:00:00","name":"France","value":24008.0},{"date":"2011-11-01T00:00:00","name":"France","value":29216.0},{"date":"2011-12-01T00:00:00","name":"France","value":6538.0},{"date":"2012-01-01T00:00:00","name":"France","value":18382.0},{"date":"2012-02-01T00:00:00","name":"France","value":18821.0},{"date":"2012-03-01T00:00:00","name":"France","value":19260.0},{"date":"2012-04-01T00:00:00","name":"France","value":19698.0},{"date":"2012-05-01T00:00:00","name":"France","value":20137.0},{"date":"2012-06-01T00:00:00","name":"France","value":20576.0},{"date":"2012-07-01T00:00:00","name":"France","value":21015.0},{"date":"2012-08-01T00:00:00","name":"France","value":21454.0},{"date":"2012-09-01T00:00:00","name":"France","value":21893.0},{"date":"2012-10-01T00:00:00","name":"France","value":22331.0},{"date":"2012-11-01T00:00:00","name":"France","value":22770.0},{"date":"2012-12-01T00:00:00","name":"France","value":23209.0},{"date":"2009-12-01T00:00:00","name":"Australia","value":271.0},{"date":"2010-01-01T00:00:00","name":"Australia","value":0.0},{"date":"2010-02-01T00:00:00","name":"Australia","value":1029.0},{"date":"2010-03-01T00:00:00","name":"Australia","value":429.0},{"date":"2010-04-01T00:00:00","name":"Australia","value":630.0},{"date":"2010-05-01T00:00:00","name":"Australia","value":1312.0},{"date":"2010-06-01T00:00:00","name":"Australia","value":3214.0},{"date":"2010-07-01T00:00:00","name":"Australia","value":631.0},{"date":"2010-08-01T00:00:00","name":"Australia","value":176.0},{"date":"2010-09-01T00:00:00","name":"Australia","value":785.0},{"date":"2010-10-01T00:00:00","name":"Australia","value":2979.0},{"date":"2010-11-01T00:00:00","name":"Australia","value":18235.0},{"date":"2010-12-01T00:00:00","name":"Australia","value":1650.0},{"date":"2011-01-01T00:00:00","name":"Australia","value":9017.0},{"date":"2011-02-01T00:00:00","name":"Australia","value":14695.0},{"date":"2011-03-01T00:00:00","name":"Australia","value":17223.0},{"date":"2011-04-01T00:00:00","name":"Australia","value":421.0},{"date":"2011-05-01T00:00:00","name":"Australia","value":13638.0},{"date":"2011-06-01T00:00:00","name":"Australia","value":25187.0},{"date":"2011-07-01T00:00:00","name":"Australia","value":4964.0},{"date":"2011-08-01T00:00:00","name":"Australia","value":22489.0},{"date":"2011-09-01T00:00:00","name":"Australia","value":5106.0},{"date":"2011-10-01T00:00:00","name":"Australia","value":17150.0},{"date":"2011-11-01T00:00:00","name":"Australia","value":7242.0},{"date":"2011-12-01T00:00:00","name":"Australia","value":0.0},{"date":"2012-01-01T00:00:00","name":"Australia","value":14154.0},{"date":"2012-02-01T00:00:00","name":"Australia","value":14724.0},{"date":"2012-03-01T00:00:00","name":"Australia","value":15295.0},{"date":"2012-04-01T00:00:00","name":"Australia","value":15865.0},{"date":"2012-05-01T00:00:00","name":"Australia","value":16435.0},{"date":"2012-06-01T00:00:00","name":"Australia","value":17006.0},{"date":"2012-07-01T00:00:00","name":"Australia","value":17576.0},{"date":"2012-08-01T00:00:00","name":"Australia","value":18147.0},{"date":"2012-09-01T00:00:00","name":"Australia","value":18717.0},{"date":"2012-10-01T00:00:00","name":"Australia","value":19287.0},{"date":"2012-11-01T00:00:00","name":"Australia","value":19858.0},{"date":"2012-12-01T00:00:00","name":"Australia","value":20428.0},{"date":"2009-12-01T00:00:00","name":"Spain","value":7754.0},{"date":"2010-01-01T00:00:00","name":"Spain","value":2122.0},{"date":"2010-02-01T00:00:00","name":"Spain","value":442.0},{"date":"2010-03-01T00:00:00","name":"Spain","value":1456.0},{"date":"2010-04-01T00:00:00","name":"Spain","value":721.0},{"date":"2010-05-01T00:00:00","name":"Spain","value":2372.0},{"date":"2010-06-01T00:00:00","name":"Spain","value":2296.0},{"date":"2010-07-01T00:00:00","name":"Spain","value":1078.0},{"date":"2010-08-01T00:00:00","name":"Spain","value":1090.0},{"date":"2010-09-01T00:00:00","name":"Spain","value":3266.0},{"date":"2010-10-01T00:00:00","name":"Spain","value":13588.0},{"date":"2010-11-01T00:00:00","name":"Spain","value":5902.0},{"date":"2010-12-01T00:00:00","name":"Spain","value":2498.0},{"date":"2011-01-01T00:00:00","name":"Spain","value":9694.0},{"date":"2011-02-01T00:00:00","name":"Spain","value":1722.0},{"date":"2011-03-01T00:00:00","name":"Spain","value":4775.0},{"date":"2011-04-01T00:00:00","name":"Spain","value":1645.0},{"date":"2011-05-01T00:00:00","name":"Spain","value":2697.0},{"date":"2011-06-01T00:00:00","name":"Spain","value":2717.0},{"date":"2011-07-01T00:00:00","name":"Spain","value":7120.0},{"date":"2011-08-01T00:00:00","name":"Spain","value":2898.0},{"date":"2011-09-01T00:00:00","name":"Spain","value":4461.0},{"date":"2011-10-01T00:00:00","name":"Spain","value":7964.0},{"date":"2011-11-01T00:00:00","name":"Spain","value":8034.0},{"date":"2011-12-01T00:00:00","name":"Spain","value":288.0},{"date":"2012-01-01T00:00:00","name":"Spain","value":5201.0},{"date":"2012-02-01T00:00:00","name":"Spain","value":5298.0},{"date":"2012-03-01T00:00:00","name":"Spain","value":5395.0},{"date":"2012-04-01T00:00:00","name":"Spain","value":5492.0},{"date":"2012-05-01T00:00:00","name":"Spain","value":5588.0},{"date":"2012-06-01T00:00:00","name":"Spain","value":5685.0},{"date":"2012-07-01T00:00:00","name":"Spain","value":5782.0},{"date":"2012-08-01T00:00:00","name":"Spain","value":5879.0},{"date":"2012-09-01T00:00:00","name":"Spain","value":5975.0},{"date":"2012-10-01T00:00:00","name":"Spain","value":6072.0},{"date":"2012-11-01T00:00:00","name":"Spain","value":6169.0},{"date":"2012-12-01T00:00:00","name":"Spain","value":6266.0},{"date":"2009-12-01T00:00:00","name":"Switzerland","value":469.0},{"date":"2010-01-01T00:00:00","name":"Switzerland","value":0.0},{"date":"2010-02-01T00:00:00","name":"Switzerland","value":397.0},{"date":"2010-03-01T00:00:00","name":"Switzerland","value":831.0},{"date":"2010-04-01T00:00:00","name":"Switzerland","value":1819.0},{"date":"2010-05-01T00:00:00","name":"Switzerland","value":9745.0},{"date":"2010-06-01T00:00:00","name":"Switzerland","value":2362.0},{"date":"2010-07-01T00:00:00","name":"Switzerland","value":569.0},{"date":"2010-08-01T00:00:00","name":"Switzerland","value":1898.0},{"date":"2010-09-01T00:00:00","name":"Switzerland","value":2274.0},{"date":"2010-10-01T00:00:00","name":"Switzerland","value":8149.0},{"date":"2010-11-01T00:00:00","name":"Switzerland","value":12440.0},{"date":"2010-12-01T00:00:00","name":"Switzerland","value":1448.0},{"date":"2011-01-01T00:00:00","name":"Switzerland","value":4031.0},{"date":"2011-02-01T00:00:00","name":"Switzerland","value":2374.0},{"date":"2011-03-01T00:00:00","name":"Switzerland","value":1590.0},{"date":"2011-04-01T00:00:00","name":"Switzerland","value":1756.0},{"date":"2011-05-01T00:00:00","name":"Switzerland","value":3450.0},{"date":"2011-06-01T00:00:00","name":"Switzerland","value":7544.0},{"date":"2011-07-01T00:00:00","name":"Switzerland","value":3518.0},{"date":"2011-08-01T00:00:00","name":"Switzerland","value":4889.0},{"date":"2011-09-01T00:00:00","name":"Switzerland","value":7524.0},{"date":"2011-10-01T00:00:00","name":"Switzerland","value":7265.0},{"date":"2011-11-01T00:00:00","name":"Switzerland","value":7916.0},{"date":"2011-12-01T00:00:00","name":"Switzerland","value":0.0},{"date":"2012-01-01T00:00:00","name":"Switzerland","value":5912.0},{"date":"2012-02-01T00:00:00","name":"Switzerland","value":6077.0},{"date":"2012-03-01T00:00:00","name":"Switzerland","value":6242.0},{"date":"2012-04-01T00:00:00","name":"Switzerland","value":6407.0},{"date":"2012-05-01T00:00:00","name":"Switzerland","value":6572.0},{"date":"2012-06-01T00:00:00","name":"Switzerland","value":6736.0},{"date":"2012-07-01T00:00:00","name":"Switzerland","value":6901.0},{"date":"2012-08-01T00:00:00","name":"Switzerland","value":7066.0},{"date":"2012-09-01T00:00:00","name":"Switzerland","value":7231.0},{"date":"2012-10-01T00:00:00","name":"Switzerland","value":7396.0},{"date":"2012-11-01T00:00:00","name":"Switzerland","value":7560.0},{"date":"2012-12-01T00:00:00","name":"Switzerland","value":7725.0},{"date":"2009-12-01T00:00:00","name":"Sweden","value":285.0},{"date":"2010-01-01T00:00:00","name":"Sweden","value":1582.0},{"date":"2010-02-01T00:00:00","name":"Sweden","value":8162.0},{"date":"2010-03-01T00:00:00","name":"Sweden","value":1357.0},{"date":"2010-04-01T00:00:00","name":"Sweden","value":15868.0},{"date":"2010-05-01T00:00:00","name":"Sweden","value":3556.0},{"date":"2010-06-01T00:00:00","name":"Sweden","value":874.0},{"date":"2010-07-01T00:00:00","name":"Sweden","value":2390.0},{"date":"2010-08-01T00:00:00","name":"Sweden","value":2312.0},{"date":"2010-09-01T00:00:00","name":"Sweden","value":2819.0},{"date":"2010-10-01T00:00:00","name":"Sweden","value":8769.0},{"date":"2010-11-01T00:00:00","name":"Sweden","value":1533.0},{"date":"2010-12-01T00:00:00","name":"Sweden","value":3834.0},{"date":"2011-01-01T00:00:00","name":"Sweden","value":3286.0},{"date":"2011-02-01T00:00:00","name":"Sweden","value":469.0},{"date":"2011-03-01T00:00:00","name":"Sweden","value":4680.0},{"date":"2011-04-01T00:00:00","name":"Sweden","value":649.0},{"date":"2011-05-01T00:00:00","name":"Sweden","value":2641.0},{"date":"2011-06-01T00:00:00","name":"Sweden","value":675.0},{"date":"2011-07-01T00:00:00","name":"Sweden","value":6692.0},{"date":"2011-08-01T00:00:00","name":"Sweden","value":1160.0},{"date":"2011-09-01T00:00:00","name":"Sweden","value":4517.0},{"date":"2011-10-01T00:00:00","name":"Sweden","value":5671.0},{"date":"2011-11-01T00:00:00","name":"Sweden","value":2322.0},{"date":"2011-12-01T00:00:00","name":"Sweden","value":238.0},{"date":"2012-01-01T00:00:00","name":"Sweden","value":2449.0},{"date":"2012-02-01T00:00:00","name":"Sweden","value":2371.0},{"date":"2012-03-01T00:00:00","name":"Sweden","value":2294.0},{"date":"2012-04-01T00:00:00","name":"Sweden","value":2217.0},{"date":"2012-05-01T00:00:00","name":"Sweden","value":2139.0},{"date":"2012-06-01T00:00:00","name":"Sweden","value":2062.0},{"date":"2012-07-01T00:00:00","name":"Sweden","value":1985.0},{"date":"2012-08-01T00:00:00","name":"Sweden","value":1908.0},{"date":"2012-09-01T00:00:00","name":"Sweden","value":1830.0},{"date":"2012-10-01T00:00:00","name":"Sweden","value":1753.0},{"date":"2012-11-01T00:00:00","name":"Sweden","value":1676.0},{"date":"2012-12-01T00:00:00","name":"Sweden","value":1598.0},{"date":"2009-12-01T00:00:00","name":"Denmark","value":1365.0},{"date":"2010-01-01T00:00:00","name":"Denmark","value":7870.0},{"date":"2010-02-01T00:00:00","name":"Denmark","value":19809.0},{"date":"2010-03-01T00:00:00","name":"Denmark","value":7595.0},{"date":"2010-04-01T00:00:00","name":"Denmark","value":748.0},{"date":"2010-05-01T00:00:00","name":"Denmark","value":0.0},{"date":"2010-06-01T00:00:00","name":"Denmark","value":2623.0},{"date":"2010-07-01T00:00:00","name":"Denmark","value":555.0},{"date":"2010-08-01T00:00:00","name":"Denmark","value":2553.0},{"date":"2010-09-01T00:00:00","name":"Denmark","value":1725.0},{"date":"2010-10-01T00:00:00","name":"Denmark","value":322.0},{"date":"2010-11-01T00:00:00","name":"Denmark","value":4041.0},{"date":"2010-12-01T00:00:00","name":"Denmark","value":2275.0},{"date":"2011-01-01T00:00:00","name":"Denmark","value":0.0},{"date":"2011-02-01T00:00:00","name":"Denmark","value":363.0},{"date":"2011-03-01T00:00:00","name":"Denmark","value":3978.0},{"date":"2011-04-01T00:00:00","name":"Denmark","value":0.0},{"date":"2011-05-01T00:00:00","name":"Denmark","value":479.0},{"date":"2011-06-01T00:00:00","name":"Denmark","value":3063.0},{"date":"2011-07-01T00:00:00","name":"Denmark","value":358.0},{"date":"2011-08-01T00:00:00","name":"Denmark","value":195.0},{"date":"2011-09-01T00:00:00","name":"Denmark","value":4510.0},{"date":"2011-10-01T00:00:00","name":"Denmark","value":1274.0},{"date":"2011-11-01T00:00:00","name":"Denmark","value":2699.0},{"date":"2011-12-01T00:00:00","name":"Denmark","value":150.0},{"date":"2012-01-01T00:00:00","name":"Denmark","value":0.0},{"date":"2012-02-01T00:00:00","name":"Denmark","value":0.0},{"date":"2012-03-01T00:00:00","name":"Denmark","value":0.0},{"date":"2012-04-01T00:00:00","name":"Denmark","value":0.0},{"date":"2012-05-01T00:00:00","name":"Denmark","value":0.0},{"date":"2012-06-01T00:00:00","name":"Denmark","value":0.0},{"date":"2012-07-01T00:00:00","name":"Denmark","value":0.0},{"date":"2012-08-01T00:00:00","name":"Denmark","value":0.0},{"date":"2012-09-01T00:00:00","name":"Denmark","value":0.0},{"date":"2012-10-01T00:00:00","name":"Denmark","value":0.0},{"date":"2012-11-01T00:00:00","name":"Denmark","value":0.0},{"date":"2012-12-01T00:00:00","name":"Denmark","value":0.0},{"date":"2009-12-01T00:00:00","name":"Belgium","value":287.0},{"date":"2010-01-01T00:00:00","name":"Belgium","value":1439.0},{"date":"2010-02-01T00:00:00","name":"Belgium","value":1685.0},{"date":"2010-03-01T00:00:00","name":"Belgium","value":629.0},{"date":"2010-04-01T00:00:00","name":"Belgium","value":2360.0},{"date":"2010-05-01T00:00:00","name":"Belgium","value":83.0},{"date":"2010-06-01T00:00:00","name":"Belgium","value":3280.0},{"date":"2010-07-01T00:00:00","name":"Belgium","value":1716.0},{"date":"2010-08-01T00:00:00","name":"Belgium","value":1575.0},{"date":"2010-09-01T00:00:00","name":"Belgium","value":1070.0},{"date":"2010-10-01T00:00:00","name":"Belgium","value":1304.0},{"date":"2010-11-01T00:00:00","name":"Belgium","value":4652.0},{"date":"2010-12-01T00:00:00","name":"Belgium","value":1910.0},{"date":"2011-01-01T00:00:00","name":"Belgium","value":1080.0},{"date":"2011-02-01T00:00:00","name":"Belgium","value":1926.0},{"date":"2011-03-01T00:00:00","name":"Belgium","value":2994.0},{"date":"2011-04-01T00:00:00","name":"Belgium","value":1788.0},{"date":"2011-05-01T00:00:00","name":"Belgium","value":2486.0},{"date":"2011-06-01T00:00:00","name":"Belgium","value":3848.0},{"date":"2011-07-01T00:00:00","name":"Belgium","value":2205.0},{"date":"2011-08-01T00:00:00","name":"Belgium","value":3140.0},{"date":"2011-09-01T00:00:00","name":"Belgium","value":3779.0},{"date":"2011-10-01T00:00:00","name":"Belgium","value":5169.0},{"date":"2011-11-01T00:00:00","name":"Belgium","value":5619.0},{"date":"2011-12-01T00:00:00","name":"Belgium","value":1288.0},{"date":"2012-01-01T00:00:00","name":"Belgium","value":3830.0},{"date":"2012-02-01T00:00:00","name":"Belgium","value":3949.0},{"date":"2012-03-01T00:00:00","name":"Belgium","value":4067.0},{"date":"2012-04-01T00:00:00","name":"Belgium","value":4185.0},{"date":"2012-05-01T00:00:00","name":"Belgium","value":4304.0},{"date":"2012-06-01T00:00:00","name":"Belgium","value":4422.0},{"date":"2012-07-01T00:00:00","name":"Belgium","value":4540.0},{"date":"2012-08-01T00:00:00","name":"Belgium","value":4659.0},{"date":"2012-09-01T00:00:00","name":"Belgium","value":4777.0},{"date":"2012-10-01T00:00:00","name":"Belgium","value":4895.0},{"date":"2012-11-01T00:00:00","name":"Belgium","value":5014.0},{"date":"2012-12-01T00:00:00","name":"Belgium","value":5132.0},{"date":"2009-12-01T00:00:00","name":"Portugal","value":2765.0},{"date":"2010-01-01T00:00:00","name":"Portugal","value":0.0},{"date":"2010-02-01T00:00:00","name":"Portugal","value":374.0},{"date":"2010-03-01T00:00:00","name":"Portugal","value":2399.0},{"date":"2010-04-01T00:00:00","name":"Portugal","value":85.0},{"date":"2010-05-01T00:00:00","name":"Portugal","value":589.0},{"date":"2010-06-01T00:00:00","name":"Portugal","value":3332.0},{"date":"2010-07-01T00:00:00","name":"Portugal","value":232.0},{"date":"2010-08-01T00:00:00","name":"Portugal","value":379.0},{"date":"2010-09-01T00:00:00","name":"Portugal","value":2880.0},{"date":"2010-10-01T00:00:00","name":"Portugal","value":2558.0},{"date":"2010-11-01T00:00:00","name":"Portugal","value":4794.0},{"date":"2010-12-01T00:00:00","name":"Portugal","value":3460.0},{"date":"2011-01-01T00:00:00","name":"Portugal","value":3479.0},{"date":"2011-02-01T00:00:00","name":"Portugal","value":1017.0},{"date":"2011-03-01T00:00:00","name":"Portugal","value":2520.0},{"date":"2011-04-01T00:00:00","name":"Portugal","value":1687.0},{"date":"2011-05-01T00:00:00","name":"Portugal","value":602.0},{"date":"2011-06-01T00:00:00","name":"Portugal","value":800.0},{"date":"2011-07-01T00:00:00","name":"Portugal","value":2175.0},{"date":"2011-08-01T00:00:00","name":"Portugal","value":1221.0},{"date":"2011-09-01T00:00:00","name":"Portugal","value":1377.0},{"date":"2011-10-01T00:00:00","name":"Portugal","value":5330.0},{"date":"2011-11-01T00:00:00","name":"Portugal","value":2336.0},{"date":"2011-12-01T00:00:00","name":"Portugal","value":2416.0},{"date":"2012-01-01T00:00:00","name":"Portugal","value":2637.0},{"date":"2012-02-01T00:00:00","name":"Portugal","value":2689.0},{"date":"2012-03-01T00:00:00","name":"Portugal","value":2742.0},{"date":"2012-04-01T00:00:00","name":"Portugal","value":2795.0},{"date":"2012-05-01T00:00:00","name":"Portugal","value":2847.0},{"date":"2012-06-01T00:00:00","name":"Portugal","value":2900.0},{"date":"2012-07-01T00:00:00","name":"Portugal","value":2953.0},{"date":"2012-08-01T00:00:00","name":"Portugal","value":3005.0},{"date":"2012-09-01T00:00:00","name":"Portugal","value":3058.0},{"date":"2012-10-01T00:00:00","name":"Portugal","value":3111.0},{"date":"2012-11-01T00:00:00","name":"Portugal","value":3163.0},{"date":"2012-12-01T00:00:00","name":"Portugal","value":3216.0},{"date":"2009-12-01T00:00:00","name":"Italy","value":422.0},{"date":"2010-01-01T00:00:00","name":"Italy","value":0.0},{"date":"2010-02-01T00:00:00","name":"Italy","value":0.0},{"date":"2010-03-01T00:00:00","name":"Italy","value":699.0},{"date":"2010-04-01T00:00:00","name":"Italy","value":1525.0},{"date":"2010-05-01T00:00:00","name":"Italy","value":1870.0},{"date":"2010-06-01T00:00:00","name":"Italy","value":232.0},{"date":"2010-07-01T00:00:00","name":"Italy","value":0.0},{"date":"2010-08-01T00:00:00","name":"Italy","value":0.0},{"date":"2010-09-01T00:00:00","name":"Italy","value":1268.0},{"date":"2010-10-01T00:00:00","name":"Italy","value":4579.0},{"date":"2010-11-01T00:00:00","name":"Italy","value":2533.0},{"date":"2010-12-01T00:00:00","name":"Italy","value":1022.0},{"date":"2011-01-01T00:00:00","name":"Italy","value":2066.0},{"date":"2011-02-01T00:00:00","name":"Italy","value":228.0},{"date":"2011-03-01T00:00:00","name":"Italy","value":1676.0},{"date":"2011-04-01T00:00:00","name":"Italy","value":737.0},{"date":"2011-05-01T00:00:00","name":"Italy","value":587.0},{"date":"2011-06-01T00:00:00","name":"Italy","value":202.0},{"date":"2011-07-01T00:00:00","name":"Italy","value":147.0},{"date":"2011-08-01T00:00:00","name":"Italy","value":1838.0},{"date":"2011-09-01T00:00:00","name":"Italy","value":279.0},{"date":"2011-10-01T00:00:00","name":"Italy","value":3329.0},{"date":"2011-11-01T00:00:00","name":"Italy","value":3875.0},{"date":"2011-12-01T00:00:00","name":"Italy","value":200.0},{"date":"2012-01-01T00:00:00","name":"Italy","value":1749.0},{"date":"2012-02-01T00:00:00","name":"Italy","value":1793.0},{"date":"2012-03-01T00:00:00","name":"Italy","value":1838.0},{"date":"2012-04-01T00:00:00","name":"Italy","value":1882.0},{"date":"2012-05-01T00:00:00","name":"Italy","value":1926.0},{"date":"2012-06-01T00:00:00","name":"Italy","value":1971.0},{"date":"2012-07-01T00:00:00","name":"Italy","value":2015.0},{"date":"2012-08-01T00:00:00","name":"Italy","value":2059.0},{"date":"2012-09-01T00:00:00","name":"Italy","value":2104.0},{"date":"2012-10-01T00:00:00","name":"Italy","value":2148.0},{"date":"2012-11-01T00:00:00","name":"Italy","value":2192.0},{"date":"2012-12-01T00:00:00","name":"Italy","value":2237.0},{"date":"2009-12-01T00:00:00","name":"Finland","value":469.0},{"date":"2010-01-01T00:00:00","name":"Finland","value":738.0},{"date":"2010-02-01T00:00:00","name":"Finland","value":0.0},{"date":"2010-03-01T00:00:00","name":"Finland","value":0.0},{"date":"2010-04-01T00:00:00","name":"Finland","value":1175.0},{"date":"2010-05-01T00:00:00","name":"Finland","value":837.0},{"date":"2010-06-01T00:00:00","name":"Finland","value":534.0},{"date":"2010-07-01T00:00:00","name":"Finland","value":836.0},{"date":"2010-08-01T00:00:00","name":"Finland","value":0.0},{"date":"2010-09-01T00:00:00","name":"Finland","value":863.0},{"date":"2010-10-01T00:00:00","name":"Finland","value":1086.0},{"date":"2010-11-01T00:00:00","name":"Finland","value":294.0},{"date":"2010-12-01T00:00:00","name":"Finland","value":652.0},{"date":"2011-01-01T00:00:00","name":"Finland","value":769.0},{"date":"2011-02-01T00:00:00","name":"Finland","value":165.0},{"date":"2011-03-01T00:00:00","name":"Finland","value":4865.0},{"date":"2011-04-01T00:00:00","name":"Finland","value":1368.0},{"date":"2011-05-01T00:00:00","name":"Finland","value":0.0},{"date":"2011-06-01T00:00:00","name":"Finland","value":289.0},{"date":"2011-07-01T00:00:00","name":"Finland","value":2436.0},{"date":"2011-08-01T00:00:00","name":"Finland","value":1096.0},{"date":"2011-09-01T00:00:00","name":"Finland","value":905.0},{"date":"2011-10-01T00:00:00","name":"Finland","value":2266.0},{"date":"2011-11-01T00:00:00","name":"Finland","value":2456.0},{"date":"2011-12-01T00:00:00","name":"Finland","value":1072.0},{"date":"2012-01-01T00:00:00","name":"Finland","value":1786.0},{"date":"2012-02-01T00:00:00","name":"Finland","value":1846.0},{"date":"2012-03-01T00:00:00","name":"Finland","value":1906.0},{"date":"2012-04-01T00:00:00","name":"Finland","value":1966.0},{"date":"2012-05-01T00:00:00","name":"Finland","value":2026.0},{"date":"2012-06-01T00:00:00","name":"Finland","value":2086.0},{"date":"2012-07-01T00:00:00","name":"Finland","value":2146.0},{"date":"2012-08-01T00:00:00","name":"Finland","value":2206.0},{"date":"2012-09-01T00:00:00","name":"Finland","value":2266.0},{"date":"2012-10-01T00:00:00","name":"Finland","value":2326.0},{"date":"2012-11-01T00:00:00","name":"Finland","value":2386.0},{"date":"2012-12-01T00:00:00","name":"Finland","value":2446.0},{"date":"2009-12-01T00:00:00","name":"Austria","value":1918.0},{"date":"2010-01-01T00:00:00","name":"Austria","value":0.0},{"date":"2010-02-01T00:00:00","name":"Austria","value":878.0},{"date":"2010-03-01T00:00:00","name":"Austria","value":685.0},{"date":"2010-04-01T00:00:00","name":"Austria","value":1388.0},{"date":"2010-05-01T00:00:00","name":"Austria","value":502.0},{"date":"2010-06-01T00:00:00","name":"Austria","value":268.0},{"date":"2010-07-01T00:00:00","name":"Austria","value":0.0},{"date":"2010-08-01T00:00:00","name":"Austria","value":1043.0},{"date":"2010-09-01T00:00:00","name":"Austria","value":1400.0},{"date":"2010-10-01T00:00:00","name":"Austria","value":956.0},{"date":"2010-11-01T00:00:00","name":"Austria","value":2513.0},{"date":"2010-12-01T00:00:00","name":"Austria","value":157.0},{"date":"2011-01-01T00:00:00","name":"Austria","value":0.0},{"date":"2011-02-01T00:00:00","name":"Austria","value":438.0},{"date":"2011-03-01T00:00:00","name":"Austria","value":1308.0},{"date":"2011-04-01T00:00:00","name":"Austria","value":584.0},{"date":"2011-05-01T00:00:00","name":"Austria","value":1049.0},{"date":"2011-06-01T00:00:00","name":"Austria","value":0.0},{"date":"2011-07-01T00:00:00","name":"Austria","value":1111.0},{"date":"2011-08-01T00:00:00","name":"Austria","value":1436.0},{"date":"2011-09-01T00:00:00","name":"Austria","value":0.0},{"date":"2011-10-01T00:00:00","name":"Austria","value":923.0},{"date":"2011-11-01T00:00:00","name":"Austria","value":1209.0},{"date":"2011-12-01T00:00:00","name":"Austria","value":523.0},{"date":"2012-01-01T00:00:00","name":"Austria","value":746.0},{"date":"2012-02-01T00:00:00","name":"Austria","value":741.0},{"date":"2012-03-01T00:00:00","name":"Austria","value":736.0},{"date":"2012-04-01T00:00:00","name":"Austria","value":731.0},{"date":"2012-05-01T00:00:00","name":"Austria","value":726.0},{"date":"2012-06-01T00:00:00","name":"Austria","value":721.0},{"date":"2012-07-01T00:00:00","name":"Austria","value":716.0},{"date":"2012-08-01T00:00:00","name":"Austria","value":711.0},{"date":"2012-09-01T00:00:00","name":"Austria","value":706.0},{"date":"2012-10-01T00:00:00","name":"Austria","value":701.0},{"date":"2012-11-01T00:00:00","name":"Austria","value":695.0},{"date":"2012-12-01T00:00:00","name":"Austria","value":690.0},{"date":"2009-12-01T00:00:00","name":"Total","value":64903.0},{"date":"2010-01-01T00:00:00","name":"Total","value":120163.0},{"date":"2010-02-01T00:00:00","name":"Total","value":86445.0},{"date":"2010-03-01T00:00:00","name":"Total","value":85473.0},{"date":"2010-04-01T00:00:00","name":"Total","value":84823.0},{"date":"2010-05-01T00:00:00","name":"Total","value":83183.0},{"date":"2010-06-01T00:00:00","name":"Total","value":88420.0},{"date":"2010-07-01T00:00:00","name":"Total","value":73490.0},{"date":"2010-08-01T00:00:00","name":"Total","value":86579.0},{"date":"2010-09-01T00:00:00","name":"Total","value":127527.0},{"date":"2010-10-01T00:00:00","name":"Total","value":137233.0},{"date":"2010-11-01T00:00:00","name":"Total","value":168661.0},{"date":"2010-12-01T00:00:00","name":"Total","value":75105.0},{"date":"2011-01-01T00:00:00","name":"Total","value":113222.0},{"date":"2011-02-01T00:00:00","name":"Total","value":74823.0},{"date":"2011-03-01T00:00:00","name":"Total","value":112689.0},{"date":"2011-04-01T00:00:00","name":"Total","value":35684.0},{"date":"2011-05-01T00:00:00","name":"Total","value":114021.0},{"date":"2011-06-01T00:00:00","name":"Total","value":118875.0},{"date":"2011-07-01T00:00:00","name":"Total","value":96940.0},{"date":"2011-08-01T00:00:00","name":"Total","value":129008.0},{"date":"2011-09-01T00:00:00","name":"Total","value":140235.0},{"date":"2011-10-01T00:00:00","name":"Total","value":172966.0},{"date":"2011-11-01T00:00:00","name":"Total","value":152654.0},{"date":"2011-12-01T00:00:00","name":"Total","value":38605.0},{"date":"2012-01-01T00:00:00","name":"Total","value":121336.0},{"date":"2012-02-01T00:00:00","name":"Total","value":122725.0},{"date":"2012-03-01T00:00:00","name":"Total","value":124115.0},{"date":"2012-04-01T00:00:00","name":"Total","value":125505.0},{"date":"2012-05-01T00:00:00","name":"Total","value":126895.0},{"date":"2012-06-01T00:00:00","name":"Total","value":128284.0},{"date":"2012-07-01T00:00:00","name":"Total","value":129674.0},{"date":"2012-08-01T00:00:00","name":"Total","value":131064.0},{"date":"2012-09-01T00:00:00","name":"Total","value":132454.0},{"date":"2012-10-01T00:00:00","name":"Total","value":133844.0},{"date":"2012-11-01T00:00:00","name":"Total","value":135233.0},{"date":"2012-12-01T00:00:00","name":"Total","value":136623.0}]